ewoksid16a/__init__.py
ewoksid16a/tasks/__init__.py
ewoksid16a/tasks/common/__init__.py
ewoksid16a/tasks/common/dataportal.py
ewoksid16a/tasks/fluo/norm_it.py
ewoksid16a/tasks/fluo/spectral_regrid.py
ewoksid16a/tasks/fluo/sum_spectra.py
ewoksid16a/tasks/fluo/sumspectrumfit.py
ewoksid16a/tasks/fluo/tiffexporter.py
ewoksid16a/tasks/fluo/weight.py
ewoksid16a/tasks/fluotomo/__init__.py
ewoksid16a/tasks/fluotomo/gallery.py
ewoksid16a/tasks/fluotomo/masterfile.py
ewoksid16a/tasks/tomo/__init__.py
ewoksid16a/tasks/tomo/extract_randdisp.py
ewoksid16a/tasks/tomo/masterfile.py
ewoksid16a/tasks/tomo/nxtomo.py
ewoksid16a/tests/__init__.py
ewoksid16a/tests/test_dummy.py
ewoksid16a-0.1.6.dist-info/licenses/LICENSE
ewoksid16a-0.1.6.dist-info/METADATA
ewoksid16a-0.1.6.dist-info/WHEEL
ewoksid16a-0.1.6.dist-info/entry_points.txt
ewoksid16a-0.1.6.dist-info/top_level.txt
ewoksid16a-0.1.6.dist-info/RECORD
