Metadata-Version: 2.4
Name: ewoksid16a
Version: 0.1.6
Summary: Data processing workflows for ID16A
Author-email: ESRF <dau-pydev@esrf.fr>
License-Expression: MIT
Project-URL: Homepage, https://gitlab.esrf.fr/workflow/ewoksapps/ewoksid16a/
Project-URL: Documentation, https://ewoksid16a.readthedocs.io/
Project-URL: Repository, https://gitlab.esrf.fr/workflow/ewoksapps/ewoksid16a/
Project-URL: Issues, https://gitlab.esrf.fr/workflow/ewoksapps/ewoksid16a/issues
Project-URL: Changelog, https://gitlab.esrf.fr/workflow/ewoksapps/ewoksid16a/-/blob/main/CHANGELOG.md
Keywords: ewoks
Classifier: Intended Audience :: Science/Research
Classifier: Programming Language :: Python :: 3
Requires-Python: >=3.9
License-File: LICENSE
Requires-Dist: numpy
Requires-Dist: h5py
Requires-Dist: matplotlib
Requires-Dist: silx
Requires-Dist: ewokscore
Requires-Dist: ewoksfluo
Requires-Dist: nxtomo
Requires-Dist: esrf_pathlib
Requires-Dist: pint
Requires-Dist: pyicat_plus
Provides-Extra: test
Requires-Dist: pytest>=7; extra == "test"
Provides-Extra: dev
Requires-Dist: ewoksid16a[test]; extra == "dev"
Requires-Dist: black>=25; extra == "dev"
Requires-Dist: flake8>=4; extra == "dev"
Requires-Dist: ruff; extra == "dev"
Requires-Dist: bandit; extra == "dev"
Requires-Dist: isort; extra == "dev"
Provides-Extra: doc
Requires-Dist: ewoksid16a[test]; extra == "doc"
Requires-Dist: sphinx>=4.5; extra == "doc"
Requires-Dist: sphinx-autodoc-typehints>=1.16; extra == "doc"
Requires-Dist: pydata-sphinx-theme; extra == "doc"
Dynamic: license-file
